[
    {
        "codigo_producto": 121,
        "nombre_producto": "Ivermectina 1%",
        "stock_anterior": 20,
        "nuevo_stock": 15,
        "motivo": "ventas",
        "fecha": "25/06/2025 23:09:49"
    },
    {
        "codigo_producto": 126,
        "nombre_producto": "Shampoo Antipulgas",
        "stock_anterior": 40,
        "nuevo_stock": 39,
        "motivo": "venta",
        "fecha": "25/06/2025 23:21:31"
    },
    {
        "codigo_producto": 121,
        "nombre_producto": "Ivermectina 1%",
        "stock_anterior": 20,
        "nuevo_stock": 0,
        "motivo": "venta",
        "fecha": "26/06/2025 10:29:55"
    }
]